version_helper.py
afeng_tools/__init__.py
afeng_tools/__version__.py
afeng_tools/aliyun_drive_tool/__init__.py
afeng_tools/aliyun_drive_tool/aliyun_drive_auth_tools.py
afeng_tools/aliyun_drive_tool/aliyun_drive_download_tools.py
afeng_tools/aliyun_drive_tool/aliyun_drive_file_tools.py
afeng_tools/aliyun_drive_tool/aliyun_drive_manage_tools.py
afeng_tools/aliyun_drive_tool/aliyun_drive_search_tools.py
afeng_tools/aliyun_drive_tool/aliyun_drive_share_tools.py
afeng_tools/aliyun_drive_tool/aliyun_drive_sign_tools.py
afeng_tools/aliyun_drive_tool/aliyun_drive_tools.py
afeng_tools/aliyun_drive_tool/aliyun_drive_upload_tools.py
afeng_tools/aliyun_drive_tool/aliyun_drive_user_tools.py
afeng_tools/aliyun_drive_tool/core/__init__.py
afeng_tools/aliyun_drive_tool/core/alipan_file_tools.py
afeng_tools/aliyun_drive_tool/core/custom_aligo.py
afeng_tools/aliyun_drive_tool/demo/__init__.py
afeng_tools/aliyun_drive_tool/demo/file_demo.py
afeng_tools/aliyun_drive_tool/demo/share_demo.py
afeng_tools/aliyun_drive_tool/demo/trans_demo.py
afeng_tools/aliyun_pan_tool/__init__.py
afeng_tools/aliyun_pan_tool/aliyun_pan_delete_tools.py
afeng_tools/aliyun_pan_tool/aliyun_pan_drive_tools.py
afeng_tools/aliyun_pan_tool/aliyun_pan_share_tools.py
afeng_tools/aliyun_pan_tool/aliyun_pan_sign_in_tools.py
afeng_tools/aliyun_pan_tool/aliyun_pan_tools.py
afeng_tools/aliyun_pan_tool/demo/__init__.py
afeng_tools/aliyun_pan_tool/demo/run_demo.py
afeng_tools/aliyun_pan_tool/demo/share_demo.py
afeng_tools/appium_tool/__init__.py
afeng_tools/appium_tool/appium_client_tool.py
afeng_tools/appium_tool/appium_options_tools.py
afeng_tools/appium_tool/appium_touch_tools.py
afeng_tools/appium_tool/mobile_adb_tools.py
afeng_tools/appium_tool/mobile_app_tools.py
afeng_tools/appium_tool/mobile_keycode.py
afeng_tools/application_tool/README.md
afeng_tools/application_tool/__init__.py
afeng_tools/application_tool/application_models.py
afeng_tools/application_tool/application_tools.py
afeng_py_tools-0.0.340.dist-info/LICENSE
afeng_py_tools-0.0.340.dist-info/METADATA
afeng_py_tools-0.0.340.dist-info/WHEEL
afeng_py_tools-0.0.340.dist-info/top_level.txt
afeng_py_tools-0.0.340.dist-info/RECORD
