Metadata-Version: 2.1
Name: afeng-py-tools
Version: 0.0.340
Summary: 阿锋的Python工具集
Author-email: chentiefeng <imchentiefeng@aliyun.com>
Maintainer-email: chentiefeng <imchentiefeng@aliyun.com>
License: 木兰宽松许可证, 第2版
Project-URL: Homepage, https://gitee.com/python-playing/afeng-py-tools
Project-URL: Documentation, https://gitee.com/python-playing/afeng-py-tools
Project-URL: Repository, https://gitee.com/python-playing/afeng-py-tools.git
Project-URL: Issues, https://gitee.com/python-playing/afeng-py-tools/issues
Project-URL: Changelog, https://gitee.com/python-playing/afeng-py-tools/blob/master/CHANGELOG.md
Keywords: 阿锋,Python工具集
Classifier: Programming Language :: Python :: 3
Classifier: License :: OSI Approved :: MIT License
Classifier: Operating System :: OS Independent
Requires-Python: >=3.10
License-File: LICENSE
